wanna/__init__.py
wanna/settings.py
wanna/utils.py
wanna/download/__init__.py
wanna/entry_points/__init__.py
wanna/entry_points/wannacli.py
wanna/misc/__init__.py
wanna/upload/__init__.py
wanna/vendors/__init__.py
wanna/vendors/aws/__init__.py
wanna/vendors/softlayer/__init__.py
wanna_transfer-0.2.2.dist-info/LICENSE
wanna_transfer-0.2.2.dist-info/METADATA
wanna_transfer-0.2.2.dist-info/WHEEL
wanna_transfer-0.2.2.dist-info/entry_points.txt
wanna_transfer-0.2.2.dist-info/top_level.txt
wanna_transfer-0.2.2.dist-info/RECORD
